kwrappers_util-0.2.79-py2.7-nspkg.pth
kwrappers/util/__init__.py
kwrappers/util/logger.py
kwrappers/util/session.py
kwrappers/util/verification.py
kwrappers_util-0.2.79.data/data/requirements.txt
kwrappers_util-0.2.79.data/data/version.txt
kwrappers_util-0.2.79.data/scripts/gav
kwrappers_util-0.2.79.dist-info/METADATA
kwrappers_util-0.2.79.dist-info/RECORD
kwrappers_util-0.2.79.dist-info/WHEEL
kwrappers_util-0.2.79.dist-info/namespace_packages.txt
kwrappers_util-0.2.79.dist-info/top_level.txt
