Metadata-Version: 2.1
Name: kwrappers-util
Version: 0.2.79
Summary: Utilities for Kwrappers.
Home-page: https://bitbucket.org/tim_kablamo/kwrappers
Author: Tim Elson
Author-email: tim.elson@kablamo.com.au
License: MIT
Platform: UNKNOWN
Requires-Dist: boto3 (>=1.6.3)
Requires-Dist: click (>=6.7)
